Workbook

Sheet Dashboard
B2: Sales Dashboard
B5: Total Revenue | E5: Total Transactions | H5: Avg. Sale Value
B6: =SUM('Sales Database'!$H$3:$H$173) -> 44672.75 | E6: =COUNTA('Sales Database'!$C$3:$C$173) -> 171 | H6: =AVERAGE('Sales Database'!$H$3:$H$173) -> 261.24415
B10: Sales by Store Location | E10: Sales by Product
B11: Store Location | C11: Total Sales | E11: Product Description | F11: Total Sales
B12: AZ | C12: =SUMIF('Sales Database'!$I$3:$I$173,B12,'Sales Database'!$H$3:$H$173) -> 13846.25 | E12: Woodlore Plus Shutters | F12: =SUMIF('Sales Database'!$E$3:$E$173,E12,'Sales Database'!$H$3:$H$173) -> 4467.75
B13: CA | C13: =SUMIF('Sales Database'!$I$3:$I$173,B13,'Sales Database'!$H$3:$H$173) -> 10655 | E13: CityLights Aluminum Blinds | F13: =SUMIF('Sales Database'!$E$3:$E$173,E13,'Sales Database'!$H$3:$H$173) -> 2508
B14: CO | C14: =SUMIF('Sales Database'!$I$3:$I$173,B14,'Sales Database'!$H$3:$H$173) -> 847.25 | E14: Ultimate Faux Wood Blinds | F14: =SUMIF('Sales Database'!$E$3:$E$173,E14,'Sales Database'!$H$3:$H$173) -> 2760
B15: NM | C15: =SUMIF('Sales Database'!$I$3:$I$173,B15,'Sales Database'!$H$3:$H$173) -> 5011.25 | E15: SmartDrape Motorized Shades | F15: =SUMIF('Sales Database'!$E$3:$E$173,E15,'Sales Database'!$H$3:$H$173) -> 14950
B16: NV | C16: =SUMIF('Sales Database'!$I$3:$I$173,B16,'Sales Database'!$H$3:$H$173) -> 10728.75 | E16: Soluna Roller Shades | F16: =SUMIF('Sales Database'!$E$3:$E$173,E16,'Sales Database'!$H$3:$H$173) -> 3220
B17: UT | C17: =SUMIF('Sales Database'!$I$3:$I$173,B17,'Sales Database'!$H$3:$H$173) -> 3584.25 | E17: Portrait Honeycomb Shades | F17: =SUMIF('Sales Database'!$E$3:$E$173,E17,'Sales Database'!$H$3:$H$173) -> 2846.25
B18: Grand Total | C18: =SUM(C12:C17) -> 44672.75 | E18: Synchrony Vertical Blinds | F18: =SUMIF('Sales Database'!$E$3:$E$173,E18,'Sales Database'!$H$3:$H$173) -> 2213.75
E19: PerfectSheer Shades | F19: =SUMIF('Sales Database'!$E$3:$E$173,E19,'Sales Database'!$H$3:$H$173) -> 3622.5
E20: Centerpiece Roman Shades | F20: =SUMIF('Sales Database'!$E$3:$E$173,E20,'Sales Database'!$H$3:$H$173) -> 2380.5
E21: Normandy Shutters | F21: =SUMIF('Sales Database'!$E$3:$E$173,E21,'Sales Database'!$H$3:$H$173) -> 5704
B22: Sales by Month
B23: Month | C23: Total Sales
B24: Jan | C24: =SUMIF('Sales Database'!$B$3:$B$173,B24,'Sales Database'!$H$3:$H$173) -> 3593
B25: Feb | C25: =SUMIF('Sales Database'!$B$3:$B$173,B25,'Sales Database'!$H$3:$H$173) -> 3666.75
B26: Mar | C26: =SUMIF('Sales Database'!$B$3:$B$173,B26,'Sales Database'!$H$3:$H$173) -> 4291.5
B27: April | C27: =SUMIF('Sales Database'!$B$3:$B$173,B27,'Sales Database'!$H$3:$H$173) -> 2674.75
B28: May | C28: =SUMIF('Sales Database'!$B$3:$B$173,B28,'Sales Database'!$H$3:$H$173) -> 2815.75
B29: June | C29: =SUMIF('Sales Database'!$B$3:$B$173,B29,'Sales Database'!$H$3:$H$173) -> 3472.25
B30: July | C30: =SUMIF('Sales Database'!$B$3:$B$173,B30,'Sales Database'!$H$3:$H$173) -> 8392.25
B31: Aug | C31: =SUMIF('Sales Database'!$B$3:$B$173,B31,'Sales Database'!$H$3:$H$173) -> 5445.25
B32: Sept | C32: =SUMIF('Sales Database'!$B$3:$B$173,B32,'Sales Database'!$H$3:$H$173) -> 3024.5
B33: Oct | C33: =SUMIF('Sales Database'!$B$3:$B$173,B33,'Sales Database'!$H$3:$H$173) -> 2610.5
B34: Nov | C34: =SUMIF('Sales Database'!$B$3:$B$173,B34,'Sales Database'!$H$3:$H$173) -> 2990
B35: Dec | C35: =SUMIF('Sales Database'!$B$3:$B$173,B35,'Sales Database'!$H$3:$H$173) -> 1696.25

Sheet Sales Database
B2: Month | C2: Transaction Number | D2: Item Code | E2: Product Description | F2: Product Cost | G2: Installation Price | H2: Total Price | I2: Store Location
B3: Jan | C3: 1001 | D3: 9822 | E3: Woodlore Plus Shutters | F3: 185 | G3: =IF(F3>100,F3*0.15,F3*0.1) -> 27.75 | H3: =F3+G3 -> 212.75 | I3: NM
B4: Jan | C4: 1002 | D4: 2877 | E4: CityLights Aluminum Blinds | F4: 95 | G4: =IF(F4>100,F4*0.15,F4*0.1) -> 9.5 | H4: =F4+G4 -> 104.5 | I4: CA
B5: Jan | C5: 1003 | D5: 2499 | E5: Ultimate Faux Wood Blinds | F5: 120 | G5: =IF(F5>100,F5*0.15,F5*0.1) -> 18 | H5: =F5+G5 -> 138 | I5: AZ
B6: Jan | C6: 1004 | D6: 8722 | E6: SmartDrape Motorized Shades | F6: 650 | G6: =IF(F6>100,F6*0.15,F6*0.1) -> 97.5 | H6: =F6+G6 -> 747.5 | I6: AZ
B7: Jan | C7: 1005 | D7: 1109 | E7: Soluna Roller Shades | F7: 140 | G7: =IF(F7>100,F7*0.15,F7*0.1) -> 21 | H7: =F7+G7 -> 161 | I7: AZ
B8: Jan | C8: 1006 | D8: 9822 | E8: Woodlore Plus Shutters | F8: 185 | G8: =IF(F8>100,F8*0.15,F8*0.1) -> 27.75 | H8: =F8+G8 -> 212.75 | I8: AZ | K8: text to columns
B9: Jan | C9: 1007 | D9: 1109 | E9: Soluna Roller Shades | F9: 140 | G9: =IF(F9>100,F9*0.15,F9*0.1) -> 21 | H9: =F9+G9 -> 161 | I9: NM | K9: if
B10: Jan | C10: 1008 | D10: 2877 | E10: CityLights Aluminum Blinds | F10: 95 | G10: =IF(F10>100,F10*0.15,F10*0.1) -> 9.5 | H10: =F10+G10 -> 104.5 | I10: NM | K10: sumif
B11: Jan | C11: 1009 | D11: 1109 | E11: Soluna Roller Shades | F11: 140 | G11: =IF(F11>100,F11*0.15,F11*0.1) -> 21 | H11: =F11+G11 -> 161 | I11: AZ | K11: filter
B12: Jan | C12: 1010 | D12: 2877 | E12: CityLights Aluminum Blinds | F12: 95 | G12: =IF(F12>100,F12*0.15,F12*0.1) -> 9.5 | H12: =F12+G12 -> 104.5 | I12: CO | K12: pivot tablees
B13: Jan | C13: 1011 | D13: 2877 | E13: CityLights Aluminum Blinds | F13: 95 | G13: =IF(F13>100,F13*0.15,F13*0.1) -> 9.5 | H13: =F13+G13 -> 104.5 | I13: AZ | K13: pie chart
B14: Jan | C14: 1012 | D14: 4421 | E14: Portrait Honeycomb Shades | F14: 165 | G14: =IF(F14>100,F14*0.15,F14*0.1) -> 24.75 | H14: =F14+G14 -> 189.75 | I14: NM
B15: Jan | C15: 1013 | D15: 9212 | E15: Synchrony Vertical Blinds | F15: 175 | G15: =IF(F15>100,F15*0.15,F15*0.1) -> 26.25 | H15: =F15+G15 -> 201.25 | I15: CO
B16: Jan | C16: 1014 | D16: 8722 | E16: SmartDrape Motorized Shades | F16: 650 | G16: =IF(F16>100,F16*0.15,F16*0.1) -> 97.5 | H16: =F16+G16 -> 747.5 | I16: CA
B17: Jan | C17: 1015 | D17: 2877 | E17: CityLights Aluminum Blinds | F17: 95 | G17: =IF(F17>100,F17*0.15,F17*0.1) -> 9.5 | H17: =F17+G17 -> 104.5 | I17: AZ
B18: Jan | C18: 1016 | D18: 2499 | E18: Ultimate Faux Wood Blinds | F18: 120 | G18: =IF(F18>100,F18*0.15,F18*0.1) -> 18 | H18: =F18+G18 -> 138 | I18: CA
B19: Feb | C19: 1017 | D19: 2242 | E19: Normandy Shutters | F19: 310 | G19: =IF(F19>100,F19*0.15,F19*0.1) -> 46.5 | H19: =F19+G19 -> 356.5 | I19: NM
B20: Feb | C20: 1018 | D20: 1109 | E20: Soluna Roller Shades | F20: 140 | G20: =IF(F20>100,F20*0.15,F20*0.1) -> 21 | H20: =F20+G20 -> 161 | I20: CA
B21: Feb | C21: 1019 | D21: 2499 | E21: Ultimate Faux Wood Blinds | F21: 120 | G21: =IF(F21>100,F21*0.15,F21*0.1) -> 18 | H21: =F21+G21 -> 138 | I21: CO
B22: Feb | C22: 1020 | D22: 2499 | E22: Ultimate Faux Wood Blinds | F22: 120 | G22: =IF(F22>100,F22*0.15,F22*0.1) -> 18 | H22: =F22+G22 -> 138 | I22: NV
B23: Feb | C23: 1021 | D23: 1109 | E23: Soluna Roller Shades | F23: 140 | G23: =IF(F23>100,F23*0.15,F23*0.1) -> 21 | H23: =F23+G23 -> 161 | I23: CO
B24: Feb | C24: 1022 | D24: 2877 | E24: CityLights Aluminum Blinds | F24: 95 | G24: =IF(F24>100,F24*0.15,F24*0.1) -> 9.5 | H24: =F24+G24 -> 104.5 | I24: UT
B25: Feb | C25: 1023 | D25: 1109 | E25: Soluna Roller Shades | F25: 140 | G25: =IF(F25>100,F25*0.15,F25*0.1) -> 21 | H25: =F25+G25 -> 161 | I25: NM
... B173: Sept | C173: 1149 | D173: 8722 | E173: SmartDrape Motorized Shades | F173: 650 | G173: =IF(F173>100,F173*0.15,F173*0.1) -> 97.5 | H173: =F173+G173 -> 747.5 | I173: AZ
E175: Sum of all items | F175: =SUM(F3:F173) -> 38945
E176: Sum items valued more than $50 | F176: =SUMIF(F3:F173,">100") -> 36665
E177: Sum of items valued at $50 less | F177: =SUMIF(F4:F174,"<100") -> 2280
